{
  "skill_id": "hermes.disease.45361128",
  "kind": "disease",
  "title": "腹滿證治合併規則",
  "subject": "腹滿",
  "abstracted_claim": "腹滿相關條文 200 條；主要方劑：小青龍湯、桂枝加芍藥湯、梔子厚朴湯、白虎湯、梔子豉湯。",
  "merged_rule_id": "MHR_DISEASE_45361128",
  "release_level": "silver",
  "consensus_score": 0.898,
  "supporting_initial_rules": [
    "IR_B0B74DF58_000598",
    "IR_B11498305_000343",
    "IR_B3E520529_000039",
    "IR_B5FF1CA1B_000380",
    "IR_B9119D083_000312",
    "IR_B9119D083_000676",
    "IR_BC2BA03C0_000043",
    "IR_JGYL_FANGLUN_000312",
    "IR_SHL_GUANZHU_000548",
    "IR_SHL_GUIBEN_000934",
    "IR_SHL_LAISU_000573",
    "IR_SHL_LEIFANG_000070",
    "IR_SHL_LUNZHU_000568",
    "IR_SHL_QJYF_000195",
    "IR_SHL_SONGBEN_000349",
    "IR_SHL_TIAOWEN_000303",
    "IR_SHL_ZHUJIE_000813",
    "IR_B07FA055B_000073",
    "IR_B0B74DF58_000247",
    "IR_B0B74DF58_000320",
    "IR_B0B74DF58_000378",
    "IR_B0B74DF58_000565",
    "IR_B0B74DF58_000603",
    "IR_B11498305_000051",
    "IR_B11498305_000088",
    "IR_B11498305_000126",
    "IR_B11498305_000253",
    "IR_B11498305_000256",
    "IR_B11498305_000345",
    "IR_B11498305_000574",
    "IR_B11498305_000575",
    "IR_B11498305_000576",
    "IR_B11498305_000583",
    "IR_B11498305_000720",
    "IR_B11498305_001129",
    "IR_B11498305_001170",
    "IR_B1CAC3ADF_000171",
    "IR_B1CAC3ADF_000263",
    "IR_B1CAC3ADF_000730",
    "IR_B3E16D849_000422",
    "IR_B3E16D849_000469",
    "IR_B3E16D849_000503",
    "IR_B3E16D849_000541",
    "IR_B3E16D849_000801",
    "IR_B3E16D849_001173",
    "IR_B3E16D849_001182",
    "IR_B3E16D849_001198",
    "IR_B3E520529_000025",
    "IR_B3E520529_000041",
    "IR_B3E520529_000118",
    "IR_B3E520529_000291",
    "IR_B3E520529_000292",
    "IR_B41512D4B_000158",
    "IR_B41512D4B_000939",
    "IR_B5C5ECAC2_000199",
    "IR_B5FF1CA1B_000056",
    "IR_B5FF1CA1B_000152",
    "IR_B5FF1CA1B_000384",
    "IR_B68E6DB3E_000014",
    "IR_B816B1DAA_000013",
    "IR_B8E444005_000296",
    "IR_B9119D083_000070",
    "IR_B9119D083_000106",
    "IR_B9119D083_000251",
    "IR_B9119D083_000330",
    "IR_B9119D083_000333",
    "IR_B9119D083_000348",
    "IR_B9119D083_000375",
    "IR_B9119D083_000470",
    "IR_B9119D083_000516",
    "IR_B9119D083_000634",
    "IR_B9119D083_000776",
    "IR_BA504DABF_000011",
    "IR_BB711944D_000845",
    "IR_BB7301DF2_000016",
    "IR_BB7301DF2_000173",
    "IR_BB7301DF2_000257",
    "IR_BB7301DF2_000299",
    "IR_BBA9FB4A6_000152",
    "IR_BBAACE965_000187",
    "IR_BBAACE965_000365",
    "IR_BBAACE965_001124",
    "IR_BC2BA03C0_000007",
    "IR_BC2BA03C0_000132",
    "IR_BC2BA03C0_000171",
    "IR_BC3C734B7_000024",
    "IR_BC3C734B7_000046",
    "IR_BC3C734B7_000047",
    "IR_BC91F4420_000178",
    "IR_BC91F4420_000315",
    "IR_BCA15D57E_000392",
    "IR_CAOSHI_FAWEI_000098",
    "IR_CAOSHI_FAWEI_000210",
    "IR_CAOSHI_FAWEI_000695",
    "IR_CAOSHI_FAWEI_001037",
    "IR_CAOSHI_FAWEI_001097",
    "IR_CAOSHI_FAWEI_001114",
    "IR_CAOSHI_FAWEI_001160",
    "IR_CAOSHI_FAWEI_001252",
    "IR_CAOSHI_FAWEI_001265",
    "IR_CAOSHI_FAWEI_001351",
    "IR_CAOSHI_FAWEI_001451",
    "IR_JGYH_ERZHU_000218",
    "IR_JGYH_ERZHU_000377",
    "IR_JGYL_FANGLUN_000090",
    "IR_JGYL_FANGLUN_000125",
    "IR_JGYL_FANGLUN_000181",
    "IR_JGYL_FANGLUN_000294",
    "IR_JGYL_FANGLUN_000298",
    "IR_JGYL_JIYI_000215",
    "IR_JGYL_JIYI_000296",
    "IR_JGYL_JIYI_000473",
    "IR_JGYL_QIANZHU_000195",
    "IR_JGYL_TIAOWEN_000090",
    "IR_JGYL_TIAOWEN_000125",
    "IR_JGYL_TIAOWEN_000181",
    "IR_JGYL_TIAOWEN_000294",
    "IR_JGYL_TIAOWEN_000298",
    "IR_JGYL_XINDIAN_000189",
    "IR_JGYL_XINDIAN_000194",
    "IR_JGYL_XINDIAN_000323",
    "IR_JG_FANGGEKUO_000023",
    "IR_SHL_GUANZHU_000044",
    "IR_SHL_GUANZHU_000085",
    "IR_SHL_GUANZHU_000255",
    "IR_SHL_GUANZHU_000443",
    "IR_SHL_GUANZHU_000456",
    "IR_SHL_GUANZHU_000457",
    "IR_SHL_GUANZHU_000458",
    "IR_SHL_GUANZHU_000471",
    "IR_SHL_GUANZHU_000474",
    "IR_SHL_GUANZHU_000549",
    "IR_SHL_GUANZHU_000552",
    "IR_SHL_GUANZHU_000717",
    "IR_SHL_GUIBEN_000158",
    "IR_SHL_GUIBEN_000310",
    "IR_SHL_GUIBEN_000340",
    "IR_SHL_GUIBEN_000341",
    "IR_SHL_GUIBEN_000437",
    "IR_SHL_GUIBEN_000521",
    "IR_SHL_GUIBEN_000572",
    "IR_SHL_GUIBEN_000892",
    "IR_SHL_GUIBEN_000905",
    "IR_SHL_GUIBEN_000939",
    "IR_SHL_GUIBEN_000941",
    "IR_SHL_GUIBEN_001355",
    "IR_SHL_GUIBEN_001359",
    "IR_SHL_GUIBEN_001427",
    "IR_SHL_GUIBEN_001630",
    "IR_SHL_GUIBEN_001642",
    "IR_SHL_LAISU_000103",
    "IR_SHL_LAISU_000104",
    "IR_SHL_LAISU_000170",
    "IR_SHL_LAISU_000366",
    "IR_SHL_LAISU_000368",
    "IR_SHL_LAISU_000369",
    "IR_SHL_LAISU_000391",
    "IR_SHL_LAISU_000427",
    "IR_SHL_LAISU_000434",
    "IR_SHL_LAISU_000462",
    "IR_SHL_LAISU_000622",
    "IR_SHL_LEIFANG_000042",
    "IR_SHL_LEIFANG_000092",
    "IR_SHL_LUNZHU_000096",
    "IR_SHL_LUNZHU_000098",
    "IR_SHL_LUNZHU_000169",
    "IR_SHL_LUNZHU_000386",
    "IR_SHL_LUNZHU_000420",
    "IR_SHL_LUNZHU_000427",
    "IR_SHL_MINGLI_000097",
    "IR_SHL_QJYF_000022",
    "IR_SHL_QJYF_000048",
    "IR_SHL_QJYF_000133",
    "IR_SHL_QJYF_000165",
    "IR_SHL_QJYF_000197",
    "IR_SHL_QJYF_000199",
    "IR_SHL_QJYF_000339",
    "IR_SHL_SONGBEN_000090",
    "IR_SHL_SONGBEN_000139",
    "IR_SHL_SONGBEN_000291",
    "IR_SHL_SONGBEN_000294",
    "IR_SHL_SONGBEN_000354",
    "IR_SHL_SONGBEN_000356",
    "IR_SHL_SUYUAN_000301",
    "IR_SHL_SUYUAN_000541",
    "IR_SHL_SUYUAN_000700",
    "IR_SHL_SUYUAN_000879",
    "IR_SHL_SUYUAN_001070",
    "IR_SHL_TIAOWEN_000044",
    "IR_SHL_TIAOWEN_000093",
    "IR_SHL_TIAOWEN_000245",
    "IR_SHL_TIAOWEN_000248",
    "IR_SHL_TIAOWEN_000308",
    "IR_SHL_TIAOWEN_000310",
    "IR_SHL_ZHUJIE_000207",
    "IR_SHL_ZHUJIE_000217",
    "IR_SHL_ZHUJIE_000316",
    "IR_SHL_ZHUJIE_000600",
    "IR_SHL_ZHUJIE_000783",
    "IR_SHL_ZHUJIE_000821"
  ],
  "supporting_rules_by_release_level": {
    "gold": [
      "IR_B0B74DF58_000598",
      "IR_B11498305_000343",
      "IR_B3E520529_000039",
      "IR_B5FF1CA1B_000380",
      "IR_B9119D083_000312",
      "IR_B9119D083_000676",
      "IR_BC2BA03C0_000043",
      "IR_JGYL_FANGLUN_000312",
      "IR_SHL_GUANZHU_000548",
      "IR_SHL_GUIBEN_000934",
      "IR_SHL_LAISU_000573",
      "IR_SHL_LEIFANG_000070",
      "IR_SHL_LUNZHU_000568",
      "IR_SHL_QJYF_000195",
      "IR_SHL_SONGBEN_000349",
      "IR_SHL_TIAOWEN_000303",
      "IR_SHL_ZHUJIE_000813"
    ],
    "silver": [
      "IR_B07FA055B_000073",
      "IR_B0B74DF58_000247",
      "IR_B0B74DF58_000320",
      "IR_B0B74DF58_000378",
      "IR_B0B74DF58_000565",
      "IR_B0B74DF58_000603",
      "IR_B11498305_000051",
      "IR_B11498305_000088",
      "IR_B11498305_000126",
      "IR_B11498305_000253",
      "IR_B11498305_000256",
      "IR_B11498305_000345",
      "IR_B11498305_000574",
      "IR_B11498305_000575",
      "IR_B11498305_000576",
      "IR_B11498305_000583",
      "IR_B11498305_000720",
      "IR_B11498305_001129",
      "IR_B11498305_001170",
      "IR_B1CAC3ADF_000171",
      "IR_B1CAC3ADF_000263",
      "IR_B1CAC3ADF_000730",
      "IR_B3E16D849_000422",
      "IR_B3E16D849_000469",
      "IR_B3E16D849_000503",
      "IR_B3E16D849_000541",
      "IR_B3E16D849_000801",
      "IR_B3E16D849_001173",
      "IR_B3E16D849_001182",
      "IR_B3E16D849_001198",
      "IR_B3E520529_000025",
      "IR_B3E520529_000041",
      "IR_B3E520529_000118",
      "IR_B3E520529_000291",
      "IR_B3E520529_000292",
      "IR_B41512D4B_000158",
      "IR_B41512D4B_000939",
      "IR_B5C5ECAC2_000199",
      "IR_B5FF1CA1B_000056",
      "IR_B5FF1CA1B_000152",
      "IR_B5FF1CA1B_000384",
      "IR_B68E6DB3E_000014",
      "IR_B816B1DAA_000013",
      "IR_B8E444005_000296",
      "IR_B9119D083_000070",
      "IR_B9119D083_000106",
      "IR_B9119D083_000251",
      "IR_B9119D083_000330",
      "IR_B9119D083_000333",
      "IR_B9119D083_000348",
      "IR_B9119D083_000375",
      "IR_B9119D083_000470",
      "IR_B9119D083_000516",
      "IR_B9119D083_000634",
      "IR_B9119D083_000776",
      "IR_BA504DABF_000011",
      "IR_BB711944D_000845",
      "IR_BB7301DF2_000016",
      "IR_BB7301DF2_000173",
      "IR_BB7301DF2_000257",
      "IR_BB7301DF2_000299",
      "IR_BBA9FB4A6_000152",
      "IR_BBAACE965_000187",
      "IR_BBAACE965_000365",
      "IR_BBAACE965_001124",
      "IR_BC2BA03C0_000007",
      "IR_BC2BA03C0_000132",
      "IR_BC2BA03C0_000171",
      "IR_BC3C734B7_000024",
      "IR_BC3C734B7_000046",
      "IR_BC3C734B7_000047",
      "IR_BC91F4420_000178",
      "IR_BC91F4420_000315",
      "IR_BCA15D57E_000392",
      "IR_CAOSHI_FAWEI_000098",
      "IR_CAOSHI_FAWEI_000210",
      "IR_CAOSHI_FAWEI_000695",
      "IR_CAOSHI_FAWEI_001037",
      "IR_CAOSHI_FAWEI_001097",
      "IR_CAOSHI_FAWEI_001114",
      "IR_CAOSHI_FAWEI_001160",
      "IR_CAOSHI_FAWEI_001252",
      "IR_CAOSHI_FAWEI_001265",
      "IR_CAOSHI_FAWEI_001351",
      "IR_CAOSHI_FAWEI_001451",
      "IR_JGYH_ERZHU_000218",
      "IR_JGYH_ERZHU_000377",
      "IR_JGYL_FANGLUN_000090",
      "IR_JGYL_FANGLUN_000125",
      "IR_JGYL_FANGLUN_000181",
      "IR_JGYL_FANGLUN_000294",
      "IR_JGYL_FANGLUN_000298",
      "IR_JGYL_JIYI_000215",
      "IR_JGYL_JIYI_000296",
      "IR_JGYL_JIYI_000473",
      "IR_JGYL_QIANZHU_000195",
      "IR_JGYL_TIAOWEN_000090",
      "IR_JGYL_TIAOWEN_000125",
      "IR_JGYL_TIAOWEN_000181",
      "IR_JGYL_TIAOWEN_000294",
      "IR_JGYL_TIAOWEN_000298",
      "IR_JGYL_XINDIAN_000189",
      "IR_JGYL_XINDIAN_000194",
      "IR_JGYL_XINDIAN_000323",
      "IR_JG_FANGGEKUO_000023",
      "IR_SHL_GUANZHU_000044",
      "IR_SHL_GUANZHU_000085",
      "IR_SHL_GUANZHU_000255",
      "IR_SHL_GUANZHU_000443",
      "IR_SHL_GUANZHU_000456",
      "IR_SHL_GUANZHU_000457",
      "IR_SHL_GUANZHU_000458",
      "IR_SHL_GUANZHU_000471",
      "IR_SHL_GUANZHU_000474",
      "IR_SHL_GUANZHU_000549",
      "IR_SHL_GUANZHU_000552",
      "IR_SHL_GUANZHU_000717",
      "IR_SHL_GUIBEN_000158",
      "IR_SHL_GUIBEN_000310",
      "IR_SHL_GUIBEN_000340",
      "IR_SHL_GUIBEN_000341",
      "IR_SHL_GUIBEN_000437",
      "IR_SHL_GUIBEN_000521",
      "IR_SHL_GUIBEN_000572",
      "IR_SHL_GUIBEN_000892",
      "IR_SHL_GUIBEN_000905",
      "IR_SHL_GUIBEN_000939",
      "IR_SHL_GUIBEN_000941",
      "IR_SHL_GUIBEN_001355",
      "IR_SHL_GUIBEN_001359",
      "IR_SHL_GUIBEN_001427",
      "IR_SHL_GUIBEN_001630",
      "IR_SHL_GUIBEN_001642",
      "IR_SHL_LAISU_000103",
      "IR_SHL_LAISU_000104",
      "IR_SHL_LAISU_000170",
      "IR_SHL_LAISU_000366",
      "IR_SHL_LAISU_000368",
      "IR_SHL_LAISU_000369",
      "IR_SHL_LAISU_000391",
      "IR_SHL_LAISU_000427",
      "IR_SHL_LAISU_000434",
      "IR_SHL_LAISU_000462",
      "IR_SHL_LAISU_000622",
      "IR_SHL_LEIFANG_000042",
      "IR_SHL_LEIFANG_000092",
      "IR_SHL_LUNZHU_000096",
      "IR_SHL_LUNZHU_000098",
      "IR_SHL_LUNZHU_000169",
      "IR_SHL_LUNZHU_000386",
      "IR_SHL_LUNZHU_000420",
      "IR_SHL_LUNZHU_000427",
      "IR_SHL_MINGLI_000097",
      "IR_SHL_QJYF_000022",
      "IR_SHL_QJYF_000048",
      "IR_SHL_QJYF_000133",
      "IR_SHL_QJYF_000165",
      "IR_SHL_QJYF_000197",
      "IR_SHL_QJYF_000199",
      "IR_SHL_QJYF_000339",
      "IR_SHL_SONGBEN_000090",
      "IR_SHL_SONGBEN_000139",
      "IR_SHL_SONGBEN_000291",
      "IR_SHL_SONGBEN_000294",
      "IR_SHL_SONGBEN_000354",
      "IR_SHL_SONGBEN_000356",
      "IR_SHL_SUYUAN_000301",
      "IR_SHL_SUYUAN_000541",
      "IR_SHL_SUYUAN_000700",
      "IR_SHL_SUYUAN_000879",
      "IR_SHL_SUYUAN_001070",
      "IR_SHL_TIAOWEN_000044",
      "IR_SHL_TIAOWEN_000093",
      "IR_SHL_TIAOWEN_000245",
      "IR_SHL_TIAOWEN_000248",
      "IR_SHL_TIAOWEN_000308",
      "IR_SHL_TIAOWEN_000310",
      "IR_SHL_ZHUJIE_000207",
      "IR_SHL_ZHUJIE_000217",
      "IR_SHL_ZHUJIE_000316",
      "IR_SHL_ZHUJIE_000600",
      "IR_SHL_ZHUJIE_000783",
      "IR_SHL_ZHUJIE_000821"
    ],
    "bronze": []
  },
  "original_evidence": [
    {
      "book_title": "傷寒纘論",
      "chapter_title": "",
      "source_unit_id": "SU_B5FF1CA1B_000588",
      "evidence_span": "太陰之為病腹滿而吐。",
      "release_level": "gold"
    },
    {
      "book_title": "傷寒大白",
      "chapter_title": "",
      "source_unit_id": "SU_B9119D083_001756",
      "evidence_span": "太陰之為病，腹滿而吐，食不下，自利益甚，時腹自痛。",
      "release_level": "gold"
    },
    {
      "book_title": "傷寒論類方",
      "chapter_title": "",
      "source_unit_id": "SU_SHL_LEIFANG_000121",
      "evidence_span": "太陰之為病，腹滿而吐，食不下，自利益甚，時腹自痛。",
      "release_level": "gold"
    },
    {
      "book_title": "傷寒論注",
      "chapter_title": "",
      "source_unit_id": "SU_SHL_LUNZHU_000963",
      "evidence_span": "太陰之為病，腹滿而吐，食不下，自利益甚，時腹自痛。",
      "release_level": "gold"
    },
    {
      "book_title": "傷寒論(宋本)",
      "chapter_title": "",
      "source_unit_id": "SU_SHL_SONGBEN_000681",
      "evidence_span": "太陰之為病，腹滿而吐，食不下，自利益甚，時腹自痛。",
      "release_level": "gold"
    },
    {
      "book_title": "傷寒論",
      "chapter_title": "",
      "source_unit_id": "SU_SHL_TIAOWEN_000528",
      "evidence_span": "太陰之為病，腹滿而吐，食不下，自利益甚，時腹自痛。",
      "release_level": "gold"
    },
    {
      "book_title": "註解傷寒論",
      "chapter_title": "",
      "source_unit_id": "SU_SHL_ZHUJIE_001283",
      "evidence_span": "太陰之為病，腹滿而吐，食不下，自利益甚，時腹自痛。",
      "release_level": "gold"
    },
    {
      "book_title": "傷寒纘論·傷寒緒論",
      "chapter_title": "",
      "source_unit_id": "SU_B11498305_000447",
      "evidence_span": "太陰之為病，腹滿而吐，食不下自利益甚，時腹自痛，若下之必胸下結鞕。",
      "release_level": "gold"
    },
    {
      "book_title": "傷寒大白",
      "chapter_title": "",
      "source_unit_id": "SU_B9119D083_000754",
      "evidence_span": "太陽之為病，腹滿而吐，食不下，自利益甚，時腹自痛，若下之，必胸滿結硬。",
      "release_level": "gold"
    },
    {
      "book_title": "傷寒總病論",
      "chapter_title": "",
      "source_unit_id": "SU_BC2BA03C0_000068",
      "evidence_span": "太陰之為病，腹滿而吐，食不下，自利益甚，時腹自痛，若下之，必胸下結硬。",
      "release_level": "gold"
    },
    {
      "book_title": "傷寒貫珠集",
      "chapter_title": "",
      "source_unit_id": "SU_SHL_GUANZHU_000373",
      "evidence_span": "太陰之為病，腹滿而吐，食不下，自利益甚，時腹自痛，若下之，必胸下結鞕。",
      "release_level": "gold"
    },
    {
      "book_title": "傷寒來蘇集",
      "chapter_title": "",
      "source_unit_id": "SU_SHL_LAISU_000387",
      "evidence_span": "太陰之為病，腹滿而吐，食不下，自利益甚，時腹自痛，若下之，必胸下結鞕。",
      "release_level": "gold"
    },
    {
      "book_title": "傷寒雜病論(桂本)",
      "chapter_title": "",
      "source_unit_id": "SU_SHL_GUIBEN_000847",
      "evidence_span": "10.12太陰之為病，腹滿而吐，食不下，自利益甚，時腹自痛，若下之，必胸下結鞕。",
      "release_level": "gold"
    },
    {
      "book_title": "傷寒論(千金翼方)",
      "chapter_title": "",
      "source_unit_id": "SU_SHL_QJYF_000247",
      "evidence_span": "太陰之為病，腹滿吐，食不下，下之益甚，時腹自痛，胸下堅結，太陰病，脈浮，可發其汗。",
      "release_level": "gold"
    },
    {
      "book_title": "金匱要略方論",
      "chapter_title": "",
      "source_unit_id": "SU_JGYL_FANGLUN_001264",
      "evidence_span": "**春秋二時，龍帶精入芹菜中，人偶食之為病，發時手青腹滿，痛不可忍，名蛟龍病，治之方：**",
      "release_level": "gold"
    },
    {
      "book_title": "傷寒總病論",
      "chapter_title": "",
      "source_unit_id": "SU_B3E520529_000042",
      "evidence_span": "太陰之為病，腹滿而吐，食不下，自利益甚，時腹自痛，若下之，必胸下結鞕自利，不渴者屬太陰，其藏有寒故也。",
      "release_level": "gold"
    },
    {
      "book_title": "傷寒恆論",
      "chapter_title": "",
      "source_unit_id": "SU_B0B74DF58_001169",
      "evidence_span": "**一、太陰之為病，腹滿而吐，食不下，自利益甚，時腹自痛，若下之，必胸下結鞕**（指胃脘部痞結脹鞕的意思。",
      "release_level": "gold"
    },
    {
      "book_title": "張卿子傷寒論",
      "chapter_title": "",
      "source_unit_id": "SU_B1CAC3ADF_000921",
      "evidence_span": "或小便不利。少腹滿。或喘者。小青龍湯主之。",
      "release_level": "silver"
    },
    {
      "book_title": "傷寒纘論·傷寒緒論",
      "chapter_title": "",
      "source_unit_id": "SU_B11498305_000131",
      "evidence_span": "發汗後腹滿者，厚朴生薑甘草，半夏人參湯主之。",
      "release_level": "silver"
    },
    {
      "book_title": "傷寒論綱目",
      "chapter_title": "",
      "source_unit_id": "SU_B3E16D849_001028",
      "evidence_span": "或噎。或小便不利少腹滿。或喘者。小青龍湯主之。",
      "release_level": "silver"
    },
    {
      "book_title": "傷寒論綱目",
      "chapter_title": "",
      "source_unit_id": "SU_B3E16D849_001088",
      "evidence_span": "或噎。或小便不利少腹滿。或喘者。小青龍湯主之。",
      "release_level": "silver"
    },
    {
      "book_title": "傷寒論綱目",
      "chapter_title": "",
      "source_unit_id": "SU_B3E16D849_001162",
      "evidence_span": "或噎。或小便不利少腹滿。或喘者。小青龍湯主之。",
      "release_level": "silver"
    },
    {
      "book_title": "傷寒論綱目",
      "chapter_title": "",
      "source_unit_id": "SU_B3E16D849_001651",
      "evidence_span": "或噎。或小便不利少腹滿。或喘者。小青龍湯主之。",
      "release_level": "silver"
    },
    {
      "book_title": "傷寒纘論·傷寒緒論",
      "chapter_title": "",
      "source_unit_id": "SU_B11498305_000168",
      "evidence_span": "傷寒下後，心煩腹滿，臥起不安者，梔子厚朴湯主之。",
      "release_level": "silver"
    },
    {
      "book_title": "傷寒論綱目",
      "chapter_title": "",
      "source_unit_id": "SU_B3E16D849_002393",
      "evidence_span": "傷寒下後。心煩腹滿。起臥不安者。梔子厚朴湯主之。",
      "release_level": "silver"
    },
    {
      "book_title": "傷寒論綱目",
      "chapter_title": "",
      "source_unit_id": "SU_B3E16D849_002411",
      "evidence_span": "傷寒下後。心煩腹滿。起臥不安者。梔子厚朴湯主之。",
      "release_level": "silver"
    },
    {
      "book_title": "傷寒論綱目",
      "chapter_title": "",
      "source_unit_id": "SU_B3E16D849_002435",
      "evidence_span": "傷寒下後。心煩腹滿。起臥不安者。梔子厚朴湯主之。",
      "release_level": "silver"
    },
    {
      "book_title": "張卿子傷寒論",
      "chapter_title": "",
      "source_unit_id": "SU_B1CAC3ADF_001101",
      "evidence_span": "傷寒下後。心煩、腹滿。臥起不安者。梔子厚朴湯主之。",
      "release_level": "silver"
    },
    {
      "book_title": "張卿子傷寒論",
      "chapter_title": "",
      "source_unit_id": "SU_B1CAC3ADF_001943",
      "evidence_span": "醫反下之。因而腹滿時痛者。屬太陰也。桂枝加芍藥湯主之。",
      "release_level": "silver"
    },
    {
      "book_title": "傷寒論綱目",
      "chapter_title": "",
      "source_unit_id": "SU_B3E16D849_000981",
      "evidence_span": "醫反下之。因而腹滿時痛者。屬太陰也。桂枝加芍藥湯主之。",
      "release_level": "silver"
    }
  ],
  "variant_set": [],
  "conflict_set": [],
  "if_profile": {},
  "then_profile": {},
  "keywords": [
    "腹滿"
  ],
  "safety_notice": "本 Skill 输出为古籍知识整理，供学习与研究参考；不构成诊断或处方建议，临床使用须由执业中医师结合患者具体情况判断。",
  "compiled_at": "2026-06-12T09:33:03Z",
  "protocol": "hermes-v5"
}