{
  "skill_id": "hermes.disease.99489485",
  "kind": "disease",
  "title": "瘀血證治合併規則",
  "subject": "瘀血",
  "abstracted_claim": "瘀血相關條文 16 條；主要方劑：抵當湯、下瘀血湯、色必黑宜抵當湯、桃花湯、脫去桃核承氣湯。",
  "merged_rule_id": "MHR_DISEASE_99489485",
  "release_level": "silver",
  "consensus_score": 0.901,
  "supporting_initial_rules": [
    "IR_B11498305_000221",
    "IR_B5FF1CA1B_000257",
    "IR_BBA9FB4A6_000152",
    "IR_CAOSHI_FAWEI_000720",
    "IR_JF_SHIYANLU_000255",
    "IR_JGYL_FANGLUN_000274",
    "IR_JGYL_TIAOWEN_000274",
    "IR_JG_FANGGEKUO_000043",
    "IR_SHL_GUIBEN_001491",
    "IR_SHL_GUIBEN_001601",
    "IR_SHL_LAISU_000265",
    "IR_SHL_MINGLI_000141",
    "IR_SHL_MINGLI_000142",
    "IR_SHL_QJYF_000181",
    "IR_SHL_QJYF_000182",
    "IR_SHL_ZHUJIE_000793"
  ],
  "supporting_rules_by_release_level": {
    "gold": [],
    "silver": [
      "IR_B11498305_000221",
      "IR_B5FF1CA1B_000257",
      "IR_BBA9FB4A6_000152",
      "IR_CAOSHI_FAWEI_000720",
      "IR_JF_SHIYANLU_000255",
      "IR_JGYL_FANGLUN_000274",
      "IR_JGYL_TIAOWEN_000274",
      "IR_JG_FANGGEKUO_000043",
      "IR_SHL_GUIBEN_001491",
      "IR_SHL_GUIBEN_001601",
      "IR_SHL_LAISU_000265",
      "IR_SHL_MINGLI_000141",
      "IR_SHL_MINGLI_000142",
      "IR_SHL_QJYF_000181",
      "IR_SHL_QJYF_000182",
      "IR_SHL_ZHUJIE_000793"
    ],
    "bronze": []
  },
  "original_evidence": [
    {
      "book_title": "傷寒雜病論(桂本)",
      "chapter_title": "",
      "source_unit_id": "SU_SHL_GUIBEN_001304",
      "evidence_span": "15.3膈間停留瘀血，若吐血色黑者，桔梗湯主之。",
      "release_level": "silver"
    },
    {
      "book_title": "金匱方歌括",
      "chapter_title": "",
      "source_unit_id": "SU_JG_FANGGEKUO_000934",
      "evidence_span": "曾經半產。瘀血在少腹不去。何以知之。其證唇口乾燥故知之以此湯主之。",
      "release_level": "silver"
    },
    {
      "book_title": "註解傷寒論",
      "chapter_title": "",
      "source_unit_id": "SU_SHL_ZHUJIE_001250",
      "evidence_span": "若瘀血在裡發黃者，則可下；此以寒濕在裡，故不可下，當從寒濕法治之。",
      "release_level": "silver"
    },
    {
      "book_title": "傷寒纘論",
      "chapter_title": "",
      "source_unit_id": "SU_B5FF1CA1B_000407",
      "evidence_span": "所以然者。本有久瘀血故令善忘屎雖硬。大便反易。其色必黑宜抵當湯主之。",
      "release_level": "silver"
    },
    {
      "book_title": "曹氏傷寒金匱發微合刊",
      "chapter_title": "",
      "source_unit_id": "SU_CAOSHI_FAWEI_000788",
      "evidence_span": "使瘀血從大便而出。其病秘愈。然則本文必便血也下。當是脫去桃核承氣湯主之七字。",
      "release_level": "silver"
    },
    {
      "book_title": "金匱要略方論",
      "chapter_title": "",
      "source_unit_id": "SU_JGYL_FANGLUN_000932",
      "evidence_span": "產婦腹痛、法當以枳實芍藥散，假令不愈者，此為腹中有瘀血著臍下，宜下瘀血湯主之；",
      "release_level": "silver"
    },
    {
      "book_title": "金匱要略方論",
      "chapter_title": "",
      "source_unit_id": "SU_JGYL_TIAOWEN_000930",
      "evidence_span": "產婦腹痛、法當以枳實芍藥散，假令不愈者，此為腹中有瘀血著臍下，宜下瘀血湯主之；",
      "release_level": "silver"
    },
    {
      "book_title": "傷寒論(千金翼方)",
      "chapter_title": "",
      "source_unit_id": "SU_SHL_QJYF_000225",
      "evidence_span": "陽明證，其人喜忘，必有蓄血，所以然者，本有久瘀血，故令喜忘，雖堅，大便必黑，抵當湯主之。",
      "release_level": "silver"
    },
    {
      "book_title": "傷寒雜病論(桂本)",
      "chapter_title": "",
      "source_unit_id": "SU_SHL_GUIBEN_001384",
      "evidence_span": "16.17師曰：產後腹痛，法當以枳實芍藥散；假令不愈，必腹中有瘀血著臍下也，下瘀血湯主之。",
      "release_level": "silver"
    },
    {
      "book_title": "傷寒纘論·傷寒緒論",
      "chapter_title": "",
      "source_unit_id": "SU_B11498305_000313",
      "evidence_span": "陽明病，其人善忘者，必有畜血，所以然者，本有久瘀血，故令善忘，糞雖鞕，大便反易，其色必黑，宜抵當湯主之。",
      "release_level": "silver"
    },
    {
      "book_title": "傷寒論(千金翼方)",
      "chapter_title": "",
      "source_unit_id": "SU_SHL_QJYF_000226",
      "evidence_span": "病者無表裡證，發熱七八日，雖脈浮數，可下之，假令下已，脈數不解，而合熱消穀喜飢，至六七日，不大便者，有瘀血，抵當湯主之。",
      "release_level": "silver"
    },
    {
      "book_title": "傷寒六書",
      "chapter_title": "",
      "source_unit_id": "SU_BBA9FB4A6_000248",
      "evidence_span": "不愈，用桂枝湯。陽明下血譫語，胸滿如結胸，夜則如見鬼，此為熱入血室，小柴胡湯。下焦蓄血，其人如狂，小腹急結，小便自利，大便黑，與夫下利，無表裡證，脈數不解，消穀易飢，多日不大便，此為瘀血，桃仁承氣湯。少陰病，下利膿血，或腹滿，下如魚腦者，桃花湯主之。",
      "release_level": "silver"
    },
    {
      "book_title": "經方實驗錄",
      "chapter_title": "",
      "source_unit_id": "SU_JF_SHIYANLU_000696",
      "evidence_span": "《千金》曰：「犀角地黃湯治傷寒及溫病，應發汗而不汗之，內蓄血者，及鼻衄吐血不盡，內餘瘀血，面黃，大便黑，消瘀血。」可以證之。《溫病條辨》曰：「太陰溫病，血從上溢者，犀角地黃湯合銀翅散治之。」又曰：「時欲漱口，不欲咽，大便黑而易者，有瘀血也，犀角地黃湯主之。",
      "release_level": "silver"
    },
    {
      "book_title": "傷寒來蘇集",
      "chapter_title": "",
      "source_unit_id": "SU_SHL_LAISU_000189",
      "evidence_span": "病人無表裏症，發熱七八日，不大便，雖脈浮數者，可下之，假令已下，脈數不解，合熱則消穀善饑，至六七日不大便者，有瘀血也，宜抵當湯，若脈數不解，而下利不止，必協熱而便膿血也。[不頭痛惡寒，為無表症，不煩燥嘔湯，為無裏症，非無熱也，七八日下，當有不大便句，故脈雖浮數，有可下之理，觀下後六七日，猶然不便可知，合熱協熱，內外熱也，前條據症推原，此條憑脈辨症，表裏熱極，陽盛陰虛，必傷陰絡，故仍不大便者，必有蓄血，熱利不止，必大便膿血矣，宜黃連阿膠湯主之，上條大便反易，知瘀血留久，是驗之於已形，此條仍不大便，知瘀血已結，是料之於未形。",
      "release_level": "silver"
    },
    {
      "book_title": "傷寒明理論",
      "chapter_title": "",
      "source_unit_id": "SU_SHL_MINGLI_000049",
      "evidence_span": "傷寒畜血，何以明之，畜血者，血在下焦，結聚而不行，畜積而不散者是也，血菀於上，而吐血者，謂之薄厥，留於下而瘀者，謂之畜血，此由太陽隨經，瘀熱在裏，血為熱所搏，結而不行，畜於下焦之所致，經曰，太陽病六七日，表證仍在，脈微而沉，反不結胸，其人發狂者，以熱在下焦，少腹當鞕滿，小便自利者，下血乃愈，抵當湯主之者是也，大抵看傷寒，必先觀兩目，次看口舌，然後自心下至小腹，以手攝按之，覺有滿鞕者，則當審而治之，如少腹覺有鞕滿，便當問其小便，若小便不利者，則是津液留結，可利小便，若小便自利者，則是畜血之證，可下瘀血，經曰，傷寒有熱，少腹滿，應小便不利，今反利者，為有血也，又曰，太陽病身黃，脈沉結，少腹鞕，小便不利者，為無血也，小便自利，其人如狂者，血證諦也，皆須抵當圓下之愈，陽明證，其人喜忘，屎雖鞕，大便反易，其色必黑，亦是畜血之證，畜血於下，所以如狂者，經所謂熱結膀胱，其人如狂者是也，血瘀於下，所以喜忘者，內經曰，血并於下，亂而喜忘者是也，二者若有其一，則為畜血證明矣，畜血之證，又有輕重焉，如狂也，喜忘也，皆畜血之甚者，須抵當湯圓以下之，如外已解，但少腹急結者，則為畜血之輕也，須桃仁承氣湯以利之，醫之妙者何也，在乎識形證，明脈息，曉虛實，知傳變，其於形證之明者，眾人所共識，又何以見其妙，必也形證之參差，眾人所未識，獨先識之，乃所以為妙，且如病人無表裏證，發熱七八日，雖脈浮數者，可下之，假令已下，脈數不解，合熱，則消穀善饑，至六七日，不大便者，此有瘀血，抵當湯主之，當不大便，六七日之際，又無喜忘如狂之證，亦無少腹鞕滿之候，當是之時，與承氣湯下者多矣，獨能處以抵當湯下之者，是為醫之妙者也，若是者，何以知其有畜血也，且脈浮而數，浮則傷氣，數則傷血，熱客於氣則脈浮，熱客於血則脈數，因下之後，浮數俱去則已，若下之後數去，其脈但浮者，則榮血間熱去，而衛氣間熱在矣，為邪氣獨留心中則飢，邪熱不殺榖，潮熱發渴也，及下之後，浮脈去而數不解者，則衛氣間熱去，而榮血間熱在矣，熱氣合并，迫血下行，胃虛脅熱，消榖善飢，血至下焦，若下不止，則血得以去，泄必便膿血也，若不大便六七日，則血不得出泄，必畜在下焦為瘀血，是須抵當湯下之，此實疾證之奇異，醫法之玄微，能審諸此者，真妙醫也。",
      "release_level": "silver"
    },
    {
      "book_title": "傷寒明理論",
      "chapter_title": "",
      "source_unit_id": "SU_SHL_MINGLI_000049",
      "evidence_span": "傷寒畜血，何以明之，畜血者，血在下焦，結聚而不行，畜積而不散者是也，血菀於上，而吐血者，謂之薄厥，留於下而瘀者，謂之畜血，此由太陽隨經，瘀熱在裏，血為熱所搏，結而不行，畜於下焦之所致，經曰，太陽病六七日，表證仍在，脈微而沉，反不結胸，其人發狂者，以熱在下焦，少腹當鞕滿，小便自利者，下血乃愈，抵當湯主之者是也，大抵看傷寒，必先觀兩目，次看口舌，然後自心下至小腹，以手攝按之，覺有滿鞕者，則當審而治之，如少腹覺有鞕滿，便當問其小便，若小便不利者，則是津液留結，可利小便，若小便自利者，則是畜血之證，可下瘀血，經曰，傷寒有熱，少腹滿，應小便不利，今反利者，為有血也，又曰，太陽病身黃，脈沉結，少腹鞕，小便不利者，為無血也，小便自利，其人如狂者，血證諦也，皆須抵當圓下之愈，陽明證，其人喜忘，屎雖鞕，大便反易，其色必黑，亦是畜血之證，畜血於下，所以如狂者，經所謂熱結膀胱，其人如狂者是也，血瘀於下，所以喜忘者，內經曰，血并於下，亂而喜忘者是也，二者若有其一，則為畜血證明矣，畜血之證，又有輕重焉，如狂也，喜忘也，皆畜血之甚者，須抵當湯圓以下之，如外已解，但少腹急結者，則為畜血之輕也，須桃仁承氣湯以利之，醫之妙者何也，在乎識形證，明脈息，曉虛實，知傳變，其於形證之明者，眾人所共識，又何以見其妙，必也形證之參差，眾人所未識，獨先識之，乃所以為妙，且如病人無表裏證，發熱七八日，雖脈浮數者，可下之，假令已下，脈數不解，合熱，則消穀善饑，至六七日，不大便者，此有瘀血，抵當湯主之，當不大便，六七日之際，又無喜忘如狂之證，亦無少腹鞕滿之候，當是之時，與承氣湯下者多矣，獨能處以抵當湯下之者，是為醫之妙者也，若是者，何以知其有畜血也，且脈浮而數，浮則傷氣，數則傷血，熱客於氣則脈浮，熱客於血則脈數，因下之後，浮數俱去則已，若下之後數去，其脈但浮者，則榮血間熱去，而衛氣間熱在矣，為邪氣獨留心中則飢，邪熱不殺榖，潮熱發渴也，及下之後，浮脈去而數不解者，則衛氣間熱去，而榮血間熱在矣，熱氣合并，迫血下行，胃虛脅熱，消榖善飢，血至下焦，若下不止，則血得以去，泄必便膿血也，若不大便六七日，則血不得出泄，必畜在下焦為瘀血，是須抵當湯下之，此實疾證之奇異，醫法之玄微，能審諸此者，真妙醫也。",
      "release_level": "silver"
    }
  ],
  "variant_set": [],
  "conflict_set": [],
  "if_profile": {},
  "then_profile": {},
  "keywords": [
    "瘀血"
  ],
  "safety_notice": "本 Skill 输出为古籍知识整理，供学习与研究参考；不构成诊断或处方建议，临床使用须由执业中医师结合患者具体情况判断。",
  "compiled_at": "2026-06-12T05:05:41Z",
  "protocol": "hermes-v5"
}